{
    "upgrades": {
    },
    "player": {
        "default": {
            "acceleration": 500,
            "max_speed": 400,
            "brake_speed": 2,
            "turn_speed": 2.5,
            "boost_power": 1.8,
            "max_health": 100,
            "max_shields": 60,
            "shield_recharge_time": 3.0,
            "shield_recharge_rate": 8.0
        },
        "armada": {
            "acceleration": 500,
            "max_speed": 450,
            "brake_speed": 2,
            "turn_speed": 2.8,
            "boost_power": 2.0,
            "max_health": 150,
            "max_shields": 75,
            "shield_recharge_time": 2.0,
            "shield_recharge_rate": 8.0
        },
        "solreign": {
            "acceleration": 750,
            "max_speed": 500,
            "brake_speed": 2,
            "turn_speed": 3.0,
            "boost_power": 2.2,
            "max_health": 100,
            "max_shields": 200,
            "shield_recharge_time": 2.0,
            "shield_recharge_rate": 10.0
        },
        "rot": {
            "acceleration": 500,
            "max_speed": 600,
            "brake_speed": 2,
            "turn_speed": 3.2,
            "boost_power": 2.2,
            "max_health": 500,
            "max_shields": 50,
            "shield_recharge_time": 3.0,
            "shield_recharge_rate": 10.0
        },
        "post": {
            "acceleration": 500,
            "max_speed": 600,
            "brake_speed": 2,
            "turn_speed": 3.5,
            "boost_power": 1.8,
            "max_health": 500,
            "max_shields": 500,
            "shield_recharge_time": 2.0,
            "shield_recharge_rate": 15.0
        }
    },
    "enemies": {
        "armada_agile": {
            "faction": "armada",
            "acceleration": 1000,
            "max_speed": 600,
            "brake_speed": 3,
            "turn_speed": 4.0,
            "boost_power": 2.0,
            "max_health": 75,
            "max_shields": 10,
            "shield_recharge_time": 2.0,
            "shield_recharge_rate": 10.0
        },
        "armada_midclasse_rocket": {
            "faction": "armada",
            "acceleration": 750,
            "max_speed": 500,
            "brake_speed": 2,
            "turn_speed": 2.5,
            "boost_power": 1.8,
            "max_health": 100,
            "max_shields": 20,
            "shield_recharge_time": 4.0,
            "shield_recharge_rate": 10.0
        },
        "armada_midclasse_projectile": {
            "faction": "armada",
            "acceleration": 750,
            "max_speed": 500,
            "brake_speed": 2,
            "turn_speed": 2.5,
            "boost_power": 1.8,
            "max_health": 100,
            "max_shields": 20,
            "shield_recharge_time": 4.0,
            "shield_recharge_rate": 10.0
        },
      "armada_destroyer": {
        "faction": "armada",
        "acceleration": 500,
        "max_speed": 600,
        "brake_speed": 2,
        "turn_speed": 2.0,
        "boost_power": 1.8,
        "max_health": 200,
        "max_shields": 40,
        "shield_recharge_time": 4.0,
        "shield_recharge_rate": 10.0
      },
      "solreign_agile": {
            "faction": "solreign",
            "acceleration": 1000,
            "max_speed": 600,
            "brake_speed": 2,
            "turn_speed": 5.0,
            "boost_power": 1.8,
            "max_health": 75,
            "max_shields": 25,
            "shield_recharge_time": 4.0,
            "shield_recharge_rate": 10.0
        },
        "solreign_midclasse_rocket": {
            "faction": "solreign",
            "acceleration": 1000,
            "max_speed": 500,
            "brake_speed": 2,
            "turn_speed": 3.0,
            "boost_power": 1.8,
            "max_health": 100,
            "max_shields": 40,
            "shield_recharge_time": 4.0,
            "shield_recharge_rate": 10.0
        },
        "solreign_midclasse_projectile": {
            "faction": "solreign",
            "acceleration": 1000,
            "max_speed": 500,
            "brake_speed": 2,
            "turn_speed": 3.0,
            "boost_power": 1.8,
            "max_health": 100,
            "max_shields": 40,
            "shield_recharge_time": 4.0,
            "shield_recharge_rate": 10.0
        },
        "solreign_destroyer": {
            "faction": "solreign",
            "acceleration": 500,
            "max_speed": 700,
            "brake_speed": 2,
            "turn_speed": 2.5,
            "boost_power": 1.8,
            "max_health": 150,
            "max_shields": 60,
            "shield_recharge_time": 4.0,
            "shield_recharge_rate": 10.0
        },"rot_agile": {
            "faction": "rot",
            "acceleration": 2000,
            "max_speed": 650,
            "brake_speed": 2,
            "turn_speed": 5.0,
            "boost_power": 1.8,
            "max_health": 100,
            "max_shields": 0,
            "shield_recharge_time": 4.0,
            "shield_recharge_rate": 10.0
        },
        "rot_midclasse_rocket": {
            "faction": "rot",
            "acceleration": 2000,
            "max_speed": 600,
            "brake_speed": 2,
            "turn_speed": 5.0,
            "boost_power": 1.8,
            "max_health": 120,
            "max_shields": 0,
            "shield_recharge_time": 4.0,
            "shield_recharge_rate": 10.0
        },
        "rot_midclasse_projectile": {
            "faction": "rot",
            "acceleration": 2000,
            "max_speed": 600,
            "brake_speed": 2,
            "turn_speed": 5.0,
            "boost_power": 1.8,
            "max_health": 150,
            "max_shields": 0,
            "shield_recharge_time": 4.0,
            "shield_recharge_rate": 10.0
        },
        "rot_destroyer": {
            "faction": "rot",
            "acceleration": 500,
            "max_speed": 400,
            "brake_speed": 2,
            "turn_speed": 2.5,
            "boost_power": 1.8,
            "max_health": 100,
            "max_shields": 20,
            "shield_recharge_time": 4.0,
            "shield_recharge_rate": 10.0
        }
    },
    "interactive": {},
    "weapons": {
        "player_cannon": {
            "type": "cannon",
            "damage": 8,
            "distance": 300,
            "reload": 0.3,
            "shot": "default"
        },
        "cannon_mk1": {
            "type": "cannon",
            "damage": 5,
            "distance": 150,
            "reload": 1.0,
            "shot": "default"
        },
        "cannon_mk2": {
            "type": "cannon",
            "damage": 8,
            "distance": 250,
            "reload": 0.8,
            "shot": "default"
        },
        "cannon_sniper": {
            "type": "cannon",
            "damage": 10,
            "distance": 30,
            "reload": 3.0,
            "shot": "sniper",
            "minimum_shoot_distance": 10,
            "maximum_shoot_distance": 30,
            "shield_multiplier": 0.6,
            "hull_multiplier": 1.2
        },
        "rocket_mk1": {
            "type": "rocket",
            "speed": 180,
            "acceleration": 250,    
            "brake_speed": 3,
            "turn_speed": 1.5,
            "lifetime": 8,
            "health": 20,
            "damage": 25,
            "reload": 3.0,
            "shot": "default"
        },
        "rocket_mk2": {
            "type": "rocket",
            "damage": 50,
            "speed": 200,
            "acceleration": 250,    
            "brake_speed": 3,
            "turn_speed": 1.9,
            "lifetime": 10,
            "health": 40,
            "reload": 2.5,
            "shot": "big_rocket"
        },
        "rocket_mk3": {
            "type": "rocket",
            "speed": 120,
            "acceleration": 250,    
            "brake_speed": 3,
            "turn_speed": 1.5,
            "lifetime": 10,
            "damage": 100,
            "health": 60,
            "reload": 3.0,
            "shot": "huge_rocket"
        },
        "player_projectile": {
            "type": "projectile",
            "speed": 700,
            "lifetime": 3,
            "damage": 3,
            "reload": 0.4,
            "shield_multiplier": 1.0,
            "hull_multiplier": 1.0,
            "shot": "kinetic"
        },
        "projectile_energy": {
            "type": "projectile",
            "speed": 350,
            "damage": 15,
            "lifetime": 4,
            "reload": 1.2,
            "shield_multiplier": 1.5,
            "hull_multiplier": 0.6,
            "shot": "energy"
        },
        "projectile_kinetic": {
            "type": "projectile",
            "speed": 600,
            "lifetime": 2,
            "damage": 2,
            "reload": 0.4,
            "shield_multiplier": 0.6,
            "minimum_shoot_distance": 50,
            "maximum_shoot_distance": 400,
            "hull_multiplier": 1.2,
            "shot": "kinetic"
        },
        "player_beam": {
            "type": "beam",
            "distance": 350,
            "damage": 5,
            "shot": "default"
        },
        "beam_mk1": {
            "type": "beam",
            "distance": 150,
            "damage": 2,
            "shot": "default"
        },
      "beam_mk2": {
        "type": "beam",
        "distance": 250,
        "damage": 3,
        "shot": "big_beam"
      },
      "beam_tooth": {
            "type": "beam",
            "distance": 18,
        "damage": 6,
        "minimum_shoot_distance": 5,
            "maximum_shoot_distance": 20,
            "shot": "tooth"
        }
    }
}